LICENSE
MANIFEST.in
README.rst
setup.py
Docs/Makefile
Docs/make.bat
Docs/source/conf.py
Docs/source/index.rst
aldryn_lightslider/__init__.py
aldryn_lightslider/admin.py
aldryn_lightslider/cms_plugins.py
aldryn_lightslider/conf.py
aldryn_lightslider/constants.py
aldryn_lightslider/fields.py
aldryn_lightslider/forms.py
aldryn_lightslider/models.py
aldryn_lightslider/tests.py
aldryn_lightslider/utils.py
aldryn_lightslider/views.py
aldryn_lightslider.egg-info/PKG-INFO
aldryn_lightslider.egg-info/SOURCES.txt
aldryn_lightslider.egg-info/dependency_links.txt
aldryn_lightslider.egg-info/top_level.txt
aldryn_lightslider/migrations/0001_initial.py
aldryn_lightslider/migrations/0002_auto_20161101_1504.py
aldryn_lightslider/migrations/__init__.py
aldryn_lightslider/static/aldryn_lightslider/js/lightslider.js
aldryn_lightslider/static/vendor/lightslider-master/.editorconfig
aldryn_lightslider/static/vendor/lightslider-master/.gitignore
aldryn_lightslider/static/vendor/lightslider-master/.jshintrc
aldryn_lightslider/static/vendor/lightslider-master/.travis.yml
aldryn_lightslider/static/vendor/lightslider-master/Gruntfile.js
aldryn_lightslider/static/vendor/lightslider-master/README.md
aldryn_lightslider/static/vendor/lightslider-master/bower.json
aldryn_lightslider/static/vendor/lightslider-master/contributing.md
aldryn_lightslider/static/vendor/lightslider-master/lightslider.jquery.json
aldryn_lightslider/static/vendor/lightslider-master/package.json
aldryn_lightslider/static/vendor/lightslider-master/demo/index.html
aldryn_lightslider/static/vendor/lightslider-master/demo/img/cS-1.jpg
aldryn_lightslider/static/vendor/lightslider-master/demo/img/cS-10.jpg
aldryn_lightslider/static/vendor/lightslider-master/demo/img/cS-11.jpg
aldryn_lightslider/static/vendor/lightslider-master/demo/img/cS-12.jpg
aldryn_lightslider/static/vendor/lightslider-master/demo/img/cS-13.jpg
aldryn_lightslider/static/vendor/lightslider-master/demo/img/cS-14.jpg
aldryn_lightslider/static/vendor/lightslider-master/demo/img/cS-15.jpg
aldryn_lightslider/static/vendor/lightslider-master/demo/img/cS-2.jpg
aldryn_lightslider/static/vendor/lightslider-master/demo/img/cS-3.jpg
