Metadata-Version: 1.1
Name: aldryn-lightslider
Version: 0.1.1
Summary: LightSlider aldryn addon and djangocms plugin.
Home-page: https://github.com/ninjabit/aldryn-lightslider
Author: Tobia Ghiraldini
Author-email: tobia.ghiraldini@ninjabit.com
License: GNU License
Platform: UNKNOWN
Classifier: Environment :: Web Environment
Classifier: Framework :: Django
Classifier: Framework :: Django :: 1.8
Classifier: Intended Audience :: Developers
Classifier: License :: OSI Approved :: GNU General Public License (GPL)
Classifier: Operating System :: OS Independent
Classifier: Programming Language :: Python
Classifier: Programming Language :: Python :: 2.7
Classifier: Programming Language :: Python :: 3
Classifier: Programming Language :: Python :: 3.4
Classifier: Programming Language :: Python :: 3.5
Classifier: Topic :: Internet :: WWW/HTTP
Classifier: Topic :: Internet :: WWW/HTTP :: Dynamic Content
